cmsstyle/__init__.py
cmsstyle/_version.py
cmsstyle/cmsstyle.py
cmsstyle-0.4.2.dist-info/METADATA
cmsstyle-0.4.2.dist-info/WHEEL
cmsstyle-0.4.2.dist-info/licenses/LICENSE
cmsstyle-0.4.2.dist-info/RECORD
